ipython_lexer.py
pygments_ipython_console-1.0.1.dist-info/LICENSE
pygments_ipython_console-1.0.1.dist-info/METADATA
pygments_ipython_console-1.0.1.dist-info/WHEEL
pygments_ipython_console-1.0.1.dist-info/entry_points.txt
pygments_ipython_console-1.0.1.dist-info/top_level.txt
pygments_ipython_console-1.0.1.dist-info/RECORD
