Metadata-Version: 2.1
Name: pygments-ipython-console
Version: 1.0.1
Summary: Syntax coloring for IPython Console (Same as Sphinx)
Home-page: https://github.com/doconce/pygments-ipython-console
Author: Matthew McKay
Author-email: mamckay@gmail.com
Maintainer: Alessandro Marin
Maintainer-email: alessandro.marin@fys.uio.no
License: BSD
Keywords: pygments ipython conf lexer
Platform: UNKNOWN
Requires-Dist: setuptools
